nebula3/Config.py
nebula3/Exception.py
nebula3/__init__.py
nebula3/common/__init__.py
nebula3/common/constants.py
nebula3/common/ttypes.py
nebula3/data/DataObject.py
nebula3/data/ResultSet.py
nebula3/data/__init__.py
nebula3/fbthrift/TMultiplexedProcessor.py
nebula3/fbthrift/TSCons.py
nebula3/fbthrift/Thrift.py
nebula3/fbthrift/__init__.py
nebula3/fbthrift/protocol/TBinaryProtocol.py
nebula3/fbthrift/protocol/TCompactProtocol.py
nebula3/fbthrift/protocol/THeaderProtocol.py
nebula3/fbthrift/protocol/TJSONProtocol.py
nebula3/fbthrift/protocol/TMultiplexedProtocol.py
nebula3/fbthrift/protocol/TProtocol.py
nebula3/fbthrift/protocol/TProtocolDecorator.py
nebula3/fbthrift/protocol/TSimpleJSONProtocol.py
nebula3/fbthrift/protocol/__init__.py
nebula3/fbthrift/protocol/exceptions.py
nebula3/fbthrift/server/TAsyncioServer.py
nebula3/fbthrift/server/TCppServer.py
nebula3/fbthrift/server/TServer.py
nebula3/fbthrift/server/__init__.py
nebula3/fbthrift/transport/THeaderTransport.py
nebula3/fbthrift/transport/THttp2Client.py
nebula3/fbthrift/transport/THttpClient.py
nebula3/fbthrift/transport/TSSLSocket.py
nebula3/fbthrift/transport/TSSLSocketOverHttpTunnel.py
nebula3/fbthrift/transport/TSocket.py
nebula3/fbthrift/transport/TSocketOverHttpTunnel.py
nebula3/fbthrift/transport/TSocketTest.py
nebula3/fbthrift/transport/TTransport.py
nebula3/fbthrift/transport/__init__.py
nebula3/fbthrift/util/BytesStrIO.py
nebula3/fbthrift/util/Decorators.py
nebula3/fbthrift/util/Recursive.py
nebula3/fbthrift/util/Serializer.py
nebula3/fbthrift/util/TCppServerTestManager.py
nebula3/fbthrift/util/TCppServerTestManagerTest.py
nebula3/fbthrift/util/TValidator.py
nebula3/fbthrift/util/__init__.py
nebula3/fbthrift/util/async_common.py
nebula3/fbthrift/util/asyncio.py
nebula3/fbthrift/util/converter.py
nebula3/fbthrift/util/fuzzer.py
nebula3/fbthrift/util/inspect.py
nebula3/fbthrift/util/randomizer.py
nebula3/fbthrift/util/remote.py
nebula3/fbthrift/util/type_inspect.py
nebula3/gclient/__init__.py
nebula3_python-3.8.2.dist-info/METADATA
nebula3_python-3.8.2.dist-info/WHEEL
nebula3_python-3.8.2.dist-info/licenses/LICENSES/Apache-2.0.txt
nebula3_python-3.8.2.dist-info/RECORD
