Metadata-Version: 2.1
Name: nebula3-python
Version: 3.8.2
Summary: Python client for NebulaGraph v3
Author-Email: vesoft-inc <info@vesoft.com>
License: Apache 2.0
Project-URL: Homepage, https://github.com/vesoft-inc/nebula-python
Requires-Python: >=3.6.2
Requires-Dist: future>=0.18.0
Requires-Dist: httplib2>=0.20.0
Requires-Dist: pytz>=2021.1
Requires-Dist: six>=1.16.0
Requires-Dist: httpx[http2]>=0.22.0
